{"__type__":"cc.SpriteAtlas","_spriteFrames":{"logo":{"__uuid__":"02B2j4SplAAoKGDnMcHKyC"},"invited":{"__uuid__":"19FFVFoeZL7oXJOqdN8++N"},"play":{"__uuid__":"5eZL5O5edE77o2XEPtNDCa"},"block1":{"__uuid__":"f8WlZEmlBHf7TbiMb4PvDi"},"block2":{"__uuid__":"68GvFNjTBEz7ZBhBTR8lAL"},"Playagain":{"__uuid__":"b1+9+uIppNSZmlpiS7q/Kf"},"block3":{"__uuid__":"ec7dDeeglEy4LfxNBmcD/j"},"share":{"__uuid__":"1fYiX2WUNF9pzRLayW0xNQ"},"HighScore":{"__uuid__":"bbRLsM+ONLQoqF2KvfdpoI"},"进度条-条":{"__uuid__":"a5Icf3BGhBNZjv6IV/tf7k"},"进度条-框":{"__uuid__":"45O+0gvnlNKISg1FN46F/J"},"newscore":{"__uuid__":"1bh49VV0VKJKDaLVC+iNBT"},"score":{"__uuid__":"09QafeL0NOa6uHwGjrB4VO"},"按钮-选中":{"__uuid__":"4fXVoEcyZFhZREIq0B+UV3"},"选择-底框":{"__uuid__":"a0M8hjgUBBy6HrLG0l5qxa"},"home_bg":{"__uuid__":"48TEN1XgpGPrXq9QIziJDB"},"skin":{"__uuid__":"a1dWG3N8VF0pDex0hQLJdK"},"选择-未选中":{"__uuid__":"0cY+/L8nJJ8bXgcryWEmpu"},"选择-选中":{"__uuid__":"5e+gVKdoxCUoMJw3YZBcO9"},"bg_white":{"__uuid__":"5e5yStNfhCAJc2qvGabEud"},"piece_1":{"__uuid__":"6e49wNh0xEYYzvCbV3SF52"},"bg":{"__uuid__":"16/5J4S2VGnJouxGTQvGAK"},"头像盒子":{"__uuid__":"35Qw9wJ/9DcK+hhJT0jjhJ"},"piece_2":{"__uuid__":"8evKXrk5RPr6h+F1pBGnI9"},"piece_4":{"__uuid__":"65bYm6bURAkbJH6adHluZ+"},"piece_3":{"__uuid__":"07lj0ivw5PPoV5PCtL6kBd"},"排行榜":{"__uuid__":"a7SjDMiEdGZ7EBzz0i3Ieo"},"icon":{"__uuid__":"2erqZ/QJpEcpGQW82j+vqz"},"人":{"__uuid__":"a1VTeWnvVH8qjE01BhgVuA"},"piece_5":{"__uuid__":"43Oo0SlopNkYolmOjmYXv9"},"fx_coinxiaosh_00":{"__uuid__":"52Qsik4VZPrLJX5wUESbfi"},"piece":{"__uuid__":"64fEX0VMxGr4rGUvV+E7lA"},"fx_coinxiaosh_01":{"__uuid__":"52Bynd8jBDgKM3gkk3g01F"},"皮肤":{"__uuid__":"6ac044rDFPPrWPI71nJblN"},"fx_coinxiaosh_02":{"__uuid__":"8dpB91u1FM44YSwDARJzCx"},"fx_coinxiaosh_03":{"__uuid__":"dfeDml6wdHlZKzdldZy9cB"},"fx_coinxiaosh_04":{"__uuid__":"aeJvnpU9NNs5xyVPdxU5Nv"},"fx_coinxiaosh_05":{"__uuid__":"c1QExRjalF7pz/47xg3Bt9"},"分享":{"__uuid__":"68Mb3q4zRMfaqOdpybigMg"}}}